fastapi_template_cli/__init__.py
fastapi_template_cli/cli.py
fastapi_template_cli/renderer.py
fastapi_template_cli/templates/beanie/api/app/__init__.py.j2
fastapi_template_cli/templates/beanie/api/app/api/__init__.py.j2
fastapi_template_cli/templates/beanie/api/app/api/v1/__init__.py.j2
fastapi_template_cli/templates/beanie/api/app/api/v1/api.py.j2
fastapi_template_cli/templates/beanie/api/app/api/v1/endpoints/__init__.py.j2
fastapi_template_cli/templates/beanie/api/app/api/v1/endpoints/test.py.j2
fastapi_template_cli/templates/beanie/api/app/database/__init__.py.j2
fastapi_template_cli/templates/beanie/api/app/database/base.py.j2
fastapi_template_cli/templates/beanie/api/app/database/mongo.py.j2
fastapi_template_cli/templates/beanie/api/app/models/__init__.py.j2
fastapi_template_cli/templates/beanie/api/app/models/users.py.j2
fastapi_template_cli/templates/beanie/api/docker/Dockerfile.j2
fastapi_template_cli/templates/beanie/modular/app/__init__.py.j2
fastapi_template_cli/templates/beanie/modular/app/database/__init__.py.j2
fastapi_template_cli/templates/beanie/modular/app/database/base.py.j2
fastapi_template_cli/templates/beanie/modular/app/database/mongo.py.j2
fastapi_template_cli/templates/beanie/modular/app/models/__init__.py.j2
fastapi_template_cli/templates/beanie/modular/app/models/users.py.j2
fastapi_template_cli/templates/beanie/modular/app/routers/__init__.py.j2
fastapi_template_cli/templates/beanie/modular/app/routers/test.py.j2
fastapi_template_cli/templates/beanie/modular/app/schemas/__init__.py.j2
fastapi_template_cli/templates/beanie/modular/app/services/__init__.py.j2
fastapi_template_cli/templates/beanie/modular/app/workers/__init__.py.j2
fastapi_template_cli/templates/beanie/modular/app/workers/celery_app.py.j2
fastapi_template_cli/templates/beanie/modular/app/workers/tasks.py.j2
fastapi_template_cli/templates/beanie/modular/docker/Dockerfile.j2
fastapi_template_cli/templates/beanie/modular/tests/__init__.py.j2
fastapi_template_cli-2.0.0.dist-info/licenses/LICENSE
fastapi_template_cli-2.0.0.dist-info/METADATA
fastapi_template_cli-2.0.0.dist-info/WHEEL
fastapi_template_cli-2.0.0.dist-info/entry_points.txt
fastapi_template_cli-2.0.0.dist-info/top_level.txt
fastapi_template_cli-2.0.0.dist-info/RECORD
