Metadata-Version: 2.4
Name: fastapi-template-cli
Version: 2.0.0
Summary: A powerful CLI tool for generating production-ready FastAPI applications with SQLAlchemy and MongoDB support
Author-email: FastAPI Template CLI <sohailahmad34280@gmail.com>
License-Expression: MIT
Project-URL: Homepage, https://github.com/Sohail342/fastapi-template
Project-URL: Documentation, https://github.com/Sohail342/fastapi-template#readme
Project-URL: Repository, https://github.com/Sohail342/fastapi-template
Project-URL: Issues, https://github.com/Sohail342/fastapi-template/issues
Keywords: fastapi,cli,scaffold,template,python,sqlalchemy,mongodb,beanie,async
Requires-Python: >=3.9
License-File: LICENSE
Requires-Dist: typer>=0.9.0
Requires-Dist: jinja2>=3.1.0
Requires-Dist: rich>=10.11.0
Requires-Dist: colorama>=0.4.6
Requires-Dist: shellingham>=1.3.0
Requires-Dist: ruff>=0.12.11
Provides-Extra: dev
Requires-Dist: pytest>=7.0.0; extra == "dev"
Requires-Dist: pytest-cov>=4.0.0; extra == "dev"
Requires-Dist: ruff>=0.6.5; extra == "dev"
Dynamic: license-file
